mrspuff/__init__.py
mrspuff/_modidx.py
mrspuff/_nbdev.py
mrspuff/autograder.py
mrspuff/pydrive2_auth.py
mrspuff/quiz.py
mrspuff/scrape.py
mrspuff/utils.py
mrspuff/viz.py
mrspuff-0.0.33.dist-info/licenses/LICENSE
mrspuff-0.0.33.dist-info/METADATA
mrspuff-0.0.33.dist-info/WHEEL
mrspuff-0.0.33.dist-info/entry_points.txt
mrspuff-0.0.33.dist-info/top_level.txt
mrspuff-0.0.33.dist-info/RECORD
