Metadata-Version: 2.4
Name: mrspuff
Version: 0.0.33
Summary: A library for Deep Learning education.
Home-page: https://github.com/drscotthawley/mrspuff/tree/master/
Author: Scott H. Hawley
Author-email: scott.hawley@belmont.edu
License: Apache Software License 2.0
Keywords: some keywords
Classifier: Development Status :: 3 - Alpha
Classifier: Intended Audience :: Developers
Classifier: Natural Language :: English
Classifier: Programming Language :: Python :: 3.6
Classifier: Programming Language :: Python :: 3.7
Classifier: Programming Language :: Python :: 3.8
Classifier: Programming Language :: Python :: 3.9
Classifier: Programming Language :: Python :: 3.10
Classifier: License :: OSI Approved :: Apache Software License
Requires-Python: >=3.6
License-File: LICENSE
Requires-Dist: fastai>=2.3.0
Requires-Dist: requests
Requires-Dist: Pillow
Requires-Dist: numpy
Requires-Dist: matplotlib
Requires-Dist: bokeh
Requires-Dist: plotly
Requires-Dist: xattr
Requires-Dist: tqdm
Requires-Dist: duckduckgo_search
Requires-Dist: ipywidgets
Requires-Dist: ddgs
Provides-Extra: dev
Requires-Dist: nbformat>=4.2.0; extra == "dev"
Dynamic: author
Dynamic: author-email
Dynamic: classifier
Dynamic: description
Dynamic: description-content-type
Dynamic: home-page
Dynamic: keywords
Dynamic: license
Dynamic: license-file
Dynamic: provides-extra
Dynamic: requires-dist
Dynamic: requires-python
Dynamic: summary
